Metadata-Version: 2.1
Name: Dre-binomial-distribution
Version: 0.1
Summary: Gaussian distributions
Author: Sobe-Olisa Andrew
Author-email: nwangenesobeolisa@gmail.com
